[{"date":"2017-03-31T10:14:26+08:00","location":"first dir/hello word","summary":"Hello This is title This can be a blog engine that not limit you.\nSimple Image \nThis is an example reference-style link.\nThen, anywhere in the document, you define your link label like this, on a line by itself:\nThis is an example inline link. (\u0026lt;p\u0026gt;This is \u0026lt;a href=\u0026quot;http://example.com/\u0026quot; title=\u0026quot;Title\u0026quot;\u0026gt;)\nThis link has no title attribute. (\u0026lt;p\u0026gt;\u0026lt;a href=\u0026quot;http://example.net/\u0026quot;\u0026gt;This link\u0026lt;/a\u0026gt; has no)\nSimple Internal MD files you can Smaple use this Hello word, to links to other md documents","title":"Hello word","truncated":false},{"date":"2017-03-21T02:00:49+08:00","location":"markdown here","summary":"Markdown Here Cheatsheet This is intended as a quick reference and showcase. For more complete info, see John Gruber\u0026rsquo;s original spec and the Github-flavored Markdown info page.\nNote that there is also a Cheatsheet specific to Markdown Here if that\u0026rsquo;s what you\u0026rsquo;re looking for. You can also check out more Markdown tools.\nTable of Contents Headers\nEmphasis\nLists\nLinks\nImages\nCode and Syntax Highlighting\nTables\nBlockquotes\nInline HTML\nHorizontal Rule","title":"Markdown Here","truncated":true},{"date":"2017-02-06T10:42:36+08:00","location":"second dir/hello word","summary":"Hello This is title This can be a blog engine that not limit you.\nThis is some image","title":"Hello word","truncated":false},{"author":"leenanxi","date":"2016-12-29T00:00:00Z","draft":true,"location":"yaml article","summary":"TITLE CONTENT","tags":["golang","hello"],"title":"Hello world","truncated":false,"type":"Page","typora-root-url":"./_DraftArticle.md"}]